tests/__init__.py
tests/dataaccess/__init__.py
tests/dataaccess/test_dataaccess.py
tests/dateutils/__init__.py
tests/dateutils/test_dateutils.py
tests/timeline/__init__.py
tests/timeline/test_parser.py
tt/__init__.py
tt/tt.py
tt/actions/__init__.py
tt/actions/read/__init__.py
tt/actions/read/calview.py
tt/actions/read/csv.py
tt/actions/read/log.py
tt/actions/read/report.py
tt/actions/read/status.py
tt/actions/utils/__init__.py
tt/actions/utils/help.py
tt/actions/utils/reportingutils.py
tt/actions/utils/utils.py
tt/actions/write/__init__.py
tt/actions/write/edit.py
tt/actions/write/note.py
tt/actions/write/start.py
tt/actions/write/stop.py
tt/actions/write/tag.py
tt/colors/__init__.py
tt/colors/colors.py
tt/dataaccess/__init__.py
tt/dataaccess/utils.py
tt/datasources/__init__.py
tt/datasources/jsondatasource.py
tt/dateutils/__init__.py
tt/dateutils/dateutils.py
tt/exceptz/BadArguments.py
tt/exceptz/TIError.py
tt/exceptz/__init__.py
tt/exceptz/exceptz.py
tt_time_tracker-1.0.4.dist-info/LICENSE
tt_time_tracker-1.0.4.dist-info/METADATA
tt_time_tracker-1.0.4.dist-info/WHEEL
tt_time_tracker-1.0.4.dist-info/entry_points.txt
tt_time_tracker-1.0.4.dist-info/top_level.txt
tt_time_tracker-1.0.4.dist-info/RECORD
