Metadata-Version: 2.1
Name: tt-time-tracker
Version: 1.0.4
Summary: A simple, precise command-line based time tracker
Home-page: https://github.com/dribnif/tt
Author: Bogdan Maxim
Author-email: bogdan.maxim@metamorphant.de
License: UNKNOWN
Platform: UNKNOWN
Requires-Python: >=3.6
Requires-Dist: colorama
Requires-Dist: lark-parser
Requires-Dist: mock
Requires-Dist: pytz
Requires-Dist: pyyaml
Requires-Dist: tzlocal (==2.1)
Provides-Extra: docs
Requires-Dist: ghp-import ; extra == 'docs'
Requires-Dist: pygreen ; extra == 'docs'
